restarting_automata/__init__.py
restarting_automata/automata_class.py
restarting_automata/monotony.py
restarting_automata/monotony.txt
restarting_automata/text_automata_class.py
restarting_automata/types.py
restarting_automata/types_linker.py
restarting_automata-0.1.1.dist-info/METADATA
restarting_automata-0.1.1.dist-info/WHEEL
restarting_automata-0.1.1.dist-info/license_files/LICENSE
restarting_automata-0.1.1.dist-info/RECORD
