Metadata-Version: 2.1
Name: restarting-automata
Version: 0.1.1
Summary: A small package for Restarting automata
Project-URL: Homepage, https://github.com/listonoh/automata_lib
Project-URL: Bug Tracker, https://github.com/listonoh/automata_lib/issues
Classifier: License :: OSI Approved :: MIT License
Classifier: Operating System :: OS Independent
Classifier: Programming Language :: Python :: 3
Requires-Python: >=3.8
Requires-Dist: colorama
Requires-Dist: graphviz
